{
  "name": "Blockland",
  "slug": "blockland",
  "year": 2007,
  "description": "Blockland is a non-linear sandbox game with no set goals, giving players the freedom to design and construct elaborate structures. Styled as a tiny minifigure, players build inside of the virtual world using bricks reminiscent of toy blocks. These structures can be built in either a single-player or multiplayer (either online or through a local area network) setting.",
  "banner_url": "/games/banner/blockland.jpg",
  "icon_url": "/games/icon/blockland.png",
  "is_public": true,
  "updated": "2019-02-07T04:05:46.878225Z",
  "provider_games": [],
  "steamid": 250340,
  "gogid": null,
  "gogslug": "",
  "humblestoreid": "",
  "id": 2241
}