{
  "id": 12301,
  "game_id": 19540,
  "game_slug": "the-awesome-adventures-of-captain-spirit",
  "name": "The Awesome Adventures of Captain Spirit",
  "year": 2018,
  "user": "citrusalex",
  "runner": "winesteam",
  "slug": "the-awesome-adventures-of-cap-steam",
  "version": "Steam",
  "description": null,
  "notes": "",
  "created_at": "2019-03-08T19:47:27.983982Z",
  "updated_at": "2019-03-08T19:47:33.563568Z",
  "draft": false,
  "published": true,
  "published_by": null,
  "rating": "",
  "steamid": 845070,
  "gogid": null,
  "gogslug": "",
  "humblestoreid": "",
  "script": {
    "game": {
      "appid": 845070
    },
    "system": {
      "env": {
        "DXVK_HUD": 0,
        "__GL_SHADER_DISK_CACHE": 1,
        "__GL_SHADER_DISK_CACHE_PATH": "$GAMEDIR"
      }
    },
    "winesteam": {
      "overrides": {
        "steamwebhelper.exe": "disabled"
      },
      "dxvk": true,
      "version": "tkg-4.0-x86_64"
    }
  },
  "content": "game:\n  appid: 845070\nsystem:\n  env:\n    DXVK_HUD: 0\n    __GL_SHADER_DISK_CACHE: 1\n    __GL_SHADER_DISK_CACHE_PATH: $GAMEDIR\nwinesteam:\n  dxvk: true\n  overrides:\n    steamwebhelper.exe: disabled\n  version: tkg-4.0-x86_64\n"
}