{
  "name": "PQ: Practical Intelligence Quotient",
  "slug": "pq-practical-intelligence-quotient",
  "year": 2005,
  "description": "Based upon psychological research, your PQ score will be determined by how quickly and effectively you solve each life-like situation. Test your wits, bend your brain, and match wits with the minds of users worldwide. A 3D puzzle game that tests players problem solving skills, PQ uses the PSP® system's Infrastructure Mode and allows players to post their PQ score on the worldwide ranking site to see how they rank against other players around the world.",
  "banner_url": "/games/banner/pq-practical-intelligence-quotient.jpg",
  "icon_url": "",
  "is_public": true,
  "updated": "2019-01-23T08:30:48.714259Z",
  "steamid": null,
  "gogslug": "",
  "humblestoreid": "",
  "id": 23283
}