{
  "name": "Pirate Adventure",
  "slug": "pirate-adventure",
  "year": 1979,
  "description": "Published by Adventure International and the second game of the series, after Adventureland, this text-based adventure game was one of many adventure games created by Scott Adams, in this case based on his wife Alexis' ideas. The setting was inspired by the novel Treasure Island and involved a quest to retrieve Long John Silver's lost treasures.",
  "banner_url": "/games/banner/pirate-adventure.jpg",
  "icon_url": "",
  "is_public": true,
  "updated": "2019-01-23T08:30:44.627258Z",
  "steamid": null,
  "gogslug": "",
  "humblestoreid": "",
  "id": 10268
}