{
  "name": "Pony Island",
  "slug": "pony-island",
  "year": 2016,
  "description": "Pony Island is a suspense puzzle game in disguise. You are in limbo, trapped in a malevolent and malfunctioning arcade machine devised by the devil himself. The devil detests having his puzzles solved and poor programming exposed; you will need to think outside the box to proceed and you will be insulted when you do.\r\n\r\nIn Pony Island you will...\r\n* Peer behind the rotting curtain of \"Pony Island\" to repair its broken code\r\n* Be forced to play along with The Devil's demented game of ponies\r\n* Explore the depths of the cryptic software system that runs His game",
  "banner_url": "/games/banner/pony-island.jpg",
  "icon_url": "/games/icon/pony-island.png",
  "is_public": true,
  "updated": "2020-05-31T00:17:52.366887Z",
  "steamid": 405640,
  "gogslug": "pony_island",
  "humblestoreid": "pony-island",
  "id": 5458
}