{
  "id": 20039,
  "game_id": 4822,
  "game_slug": "the-flame-in-the-flood",
  "name": "The Flame in the Flood",
  "year": 2016,
  "user": "schmarky",
  "runner": "wine",
  "slug": "the-flame-in-the-flood-gog",
  "version": "GOG",
  "description": null,
  "notes": "",
  "created_at": "2020-04-27T17:09:20.416306Z",
  "updated_at": "2020-04-27T17:09:20.416329Z",
  "draft": true,
  "published": false,
  "published_by": null,
  "rating": "",
  "steamid": 318600,
  "gogid": 1452692111,
  "gogslug": "the_flame_in_the_flood",
  "humbleid": "",
  "humblestoreid": "",
  "humblestoreid_real": "",
  "script": {
    "files": [
      {
        "goginstaller": "N/A:Please select the GOG.com Windows installer"
      }
    ],
    "game": {
      "arch": "win64",
      "exe": "drive_c/GOG Games/The Flame in the Flood/RiverGame.exe",
      "prefix": "$GAMEDIR"
    },
    "installer": [
      {
        "task": {
          "arch": "win64",
          "name": "create_prefix",
          "prefix": "$GAMEDIR"
        }
      },
      {
        "task": {
          "arch": "win64",
          "args": "/LANG=English /SP- /SUPPRESSMSGBOXES",
          "executable": "goginstaller",
          "name": "wineexec",
          "prefix": "$GAMEDIR"
        }
      }
    ]
  },
  "content": "files:\n- goginstaller: N/A:Please select the GOG.com Windows installer\ngame:\n  arch: win64\n  exe: drive_c/GOG Games/The Flame in the Flood/RiverGame.exe\n  prefix: $GAMEDIR\ninstaller:\n- task:\n    arch: win64\n    name: create_prefix\n    prefix: $GAMEDIR\n- task:\n    arch: win64\n    args: /LANG=English /SP- /SUPPRESSMSGBOXES\n    executable: goginstaller\n    name: wineexec\n    prefix: $GAMEDIR\n"
}