{
  "id": 8613,
  "game_id": 15238,
  "game_slug": "warhammer-40000-inquisitor-martyr",
  "name": "Warhammer 40,000: Inquisitor - Martyr",
  "year": 2018,
  "user": "TuiorGames",
  "runner": "winesteam",
  "slug": "warhammer-40000-inquisitor-ma-steam",
  "version": "Steam",
  "description": null,
  "notes": "",
  "created_at": "2018-06-09T00:55:03.551892Z",
  "updated_at": "2020-01-31T02:38:30.547795Z",
  "draft": true,
  "published": true,
  "published_by": null,
  "rating": "",
  "steamid": 527430,
  "gogid": null,
  "gogslug": "",
  "humblestoreid": "",
  "script": {
    "game": {
      "appid": 527430,
      "arch": "win64"
    },
    "winesteam": {
      "Desktop": true
    }
  },
  "content": "game:\n  appid: 527430\n  arch: win64\nwinesteam:\n  Desktop: true\n"
}