{
  "name": "Pink Hour",
  "slug": "pink-hour",
  "year": 2015,
  "description": "This is a cute and fancy action game that lets you mess around and have fun to your heart's content\r\nPlaying as the pink-clad office lady appearing in Kero Blaster - the 2D scrolling action game - you must make your way through a cave to escape the enemy's clutches. \r\nFind the missing documents and defeat your opponents by jumping over them. \r\nClear the game by returning safely back to the office with the reclaimed documents in hand.\r\n\r\nHard mode includes a new special ending that you won't want to miss! \r\n\r\nYou can also play this game to test your system environment for \"Kero Blaster\". \r\n",
  "banner_url": "/games/banner/pink-hour.jpg",
  "icon_url": "/games/icon/pink-hour.png",
  "is_public": true,
  "updated": "2019-01-23T08:30:44.502600Z",
  "steamid": 409670,
  "gogslug": "",
  "humblestoreid": "",
  "id": 5476
}