{
  "id": 1560,
  "game_id": 388,
  "game_slug": "the-witcher-enhanced-edition",
  "name": "The Witcher: Enhanced Edition",
  "year": 2007,
  "user": "Freso",
  "runner": "winesteam",
  "slug": "the-witcher-enhanced-edition-steam",
  "version": "Steam",
  "description": null,
  "notes": "",
  "created_at": "2015-06-09T00:21:08.383000Z",
  "updated_at": "2020-01-31T02:38:27.228171Z",
  "draft": false,
  "published": true,
  "published_by": 1,
  "rating": "5",
  "steamid": 20900,
  "gogid": 1207658924,
  "gogslug": "the_witcher",
  "humblestoreid": "",
  "script": {
    "game": {
      "appid": 20900,
      "prefix": "$GAMEDIR/prefix"
    },
    "system": {
      "env": {
        "__GL_SHADER_DISK_CACHE_PATH": "$GAMEDIR",
        "mesa_glthread": "true",
        "__GL_THREADED_OPTIMIZATIONS": "1"
      }
    },
    "installer": [
      {
        "task": {
          "app": "d3dx9_35",
          "silent": true,
          "prefix": "$GAMEDIR",
          "name": "winetricks"
        }
      },
      {
        "task": {
          "value": "enabled",
          "path": "HKEY_CURRENT_USER\\Software\\Wine\\Direct3D",
          "key": "CheckFloatConstants",
          "prefix": "$GAMEDIR",
          "name": "set_regedit"
        }
      }
    ],
    "winesteam": {
      "esync": "true"
    }
  },
  "content": "game:\n  appid: 20900\n  prefix: $GAMEDIR/prefix\ninstaller:\n- task:\n    app: d3dx9_35\n    name: winetricks\n    prefix: $GAMEDIR\n    silent: true\n- task:\n    key: CheckFloatConstants\n    name: set_regedit\n    path: HKEY_CURRENT_USER\\Software\\Wine\\Direct3D\n    prefix: $GAMEDIR\n    value: enabled\nsystem:\n  env:\n    __GL_SHADER_DISK_CACHE_PATH: $GAMEDIR\n    __GL_THREADED_OPTIMIZATIONS: '1'\n    mesa_glthread: 'true'\nwinesteam:\n  esync: 'true'\n"
}