{
  "id": 20082,
  "game_id": 19994,
  "game_slug": "welcome-to-the-game-ii",
  "name": "Welcome to the Game II",
  "year": null,
  "user": "nagaze",
  "runner": "browser",
  "slug": "welcome-to-the-game-ii-sla",
  "version": "sla",
  "description": null,
  "notes": "",
  "created_at": "2020-04-28T16:36:23.882828Z",
  "updated_at": "2020-04-28T16:36:23.882854Z",
  "draft": true,
  "published": false,
  "published_by": null,
  "rating": "",
  "steamid": 720250,
  "gogid": null,
  "gogslug": "",
  "humblestoreid": "",
  "script": {
    "game": {
      "appid": 720250
    }
  },
  "content": "game:\n  appid: 720250\n"
}