{
  "name": "DarkMaus",
  "slug": "darkmaus",
  "year": 2016,
  "description": "In DarkMaus, you play a lonely wanderer searching for what's left in a corrupted world. The odds are against you - you will certainly perish. \r\n\r\nNote: This game is designed for an Xbox Controller, but mouse / keyboard works too.\r\n\r\n* A worthy challenge - combat in DarkMaus is thoughtful and skill based. Enemies force you to be reactive to survive, and punish any greedy moves or mistakes. You'll start out swearing that it's impossible, and end up a god among Mäuse.\r\n* Death Echo - each time you die, an ally ghost is summoned that retraces your steps, fighting by your side. With time you can collect multiple ally ghosts and choose their weapons for extra strategy opportunities.\r\n* A dark world to explore - search for answers and secrets in the desolate land of Hazath, whose inhabitants have gone feral.\r\n* Combat style variety - from spears to greatswords and bows to fireballs, DarkMaus has a large number of viable builds and playstyles, each with their own strengths and weaknesses.",
  "banner_url": "/games/banner/darkmaus.jpg",
  "icon_url": "/games/icon/darkmaus.png",
  "is_public": true,
  "updated": "2019-10-11T02:18:50.108433Z",
  "provider_games": [],
  "steamid": 406130,
  "gogid": null,
  "gogslug": "",
  "humblestoreid": "",
  "id": 10265
}