{
  "id": 2225,
  "game_id": 4341,
  "game_slug": "victor-vran",
  "name": "Victor Vran",
  "year": 2015,
  "user": "Lulu",
  "runner": "linux",
  "slug": "victor-vran-gog",
  "version": "GOG",
  "description": "",
  "notes": "",
  "created_at": "2016-06-29T05:55:15.521153Z",
  "updated_at": "2016-07-05T00:45:28.168645Z",
  "draft": false,
  "published": true,
  "published_by": null,
  "rating": "",
  "steamid": 345180,
  "gogid": 1433856545,
  "gogslug": "victor_vran",
  "humblestoreid": "",
  "script": {
    "files": [
      {
        "game": "N/A: Plese select the GOG.com Linux installer"
      },
      {
        "unzip": "http://lutris.net/files/tools/unzip.tar.gz"
      }
    ],
    "exe": "Game/start.sh",
    "gogid": "victor_vran",
    "installer": [
      {
        "extract": {
          "dst": "$CACHE",
          "file": "$unzip"
        }
      },
      {
        "execute": {
          "args": "$game -d \"$GAMEDIR\" \"data/noarch/*\"",
          "file": "$CACHE/unzip",
          "description": "Extracting game data, it will take a while..."
        }
      },
      {
        "rename": {
          "dst": "$GAMEDIR/Game",
          "src": "$GAMEDIR/data/noarch"
        }
      }
    ]
  },
  "content": "exe: Game/start.sh\nfiles:\n- game: 'N/A: Plese select the GOG.com Linux installer'\n- unzip: http://lutris.net/files/tools/unzip.tar.gz\ngogid: victor_vran\ninstaller:\n- extract:\n    dst: $CACHE\n    file: $unzip\n- execute:\n    args: $game -d \"$GAMEDIR\" \"data/noarch/*\"\n    description: Extracting game data, it will take a while...\n    file: $CACHE/unzip\n- rename:\n    dst: $GAMEDIR/Game\n    src: $GAMEDIR/data/noarch\n"
}