{
  "id": 1775,
  "game_id": 118,
  "game_slug": "quake-mission-pack-2-dissolution-of-eternity",
  "name": "Quake Mission Pack 2: Dissolution of Eternity",
  "year": 1997,
  "user": "strider",
  "runner": "linux",
  "slug": "quake-mission-pack-2-dissolut-darkplaces-steam",
  "version": "Darkplaces + Steam",
  "description": "",
  "notes": "",
  "created_at": "2015-12-28T20:02:45.369911Z",
  "updated_at": "2015-12-28T20:04:48.178440Z",
  "draft": false,
  "published": true,
  "published_by": null,
  "rating": "",
  "steamid": 9030,
  "gogid": null,
  "gogslug": "",
  "humblestoreid": "",
  "script": {
    "exe64": "darkplaces-linux-x86_64-glx",
    "installer": [
      {
        "merge": {
          "src": "steam-data",
          "dst": "$GAMEDIR/rogue"
        }
      }
    ],
    "files": [
      {
        "steam-data": "$STEAM:9030:rogue"
      }
    ],
    "game": {
      "args": "-game rogue -rogue"
    },
    "requires": "quake-darkplaces-steam",
    "exe": "darkplaces-linux-686-glx"
  },
  "content": "exe: darkplaces-linux-686-glx\nexe64: darkplaces-linux-x86_64-glx\nfiles:\n- steam-data: $STEAM:9030:rogue\ngame:\n  args: -game rogue -rogue\ninstaller:\n- merge:\n    dst: $GAMEDIR/rogue\n    src: steam-data\nrequires: quake-darkplaces-steam\n"
}