{
  "id": 12976,
  "game_id": 1305,
  "game_slug": "lego-harry-potter-years-5-7",
  "name": "LEGO Harry Potter: Years 5-7",
  "year": 2012,
  "user": "cxf",
  "runner": "wine",
  "slug": "lego-harry-potter-years-5-7-gog",
  "version": "GOG",
  "description": null,
  "notes": "",
  "created_at": "2019-04-20T08:03:13.689146Z",
  "updated_at": "2019-04-20T08:03:19.029654Z",
  "draft": false,
  "published": true,
  "published_by": null,
  "rating": "",
  "steamid": 204120,
  "gogid": 1423058931,
  "gogslug": "lego_harry_potter_years_57",
  "humblestoreid": "",
  "script": {
    "game": {
      "arch": "win32",
      "prefix": "$GAMEDIR",
      "exe": "drive_c/GOG Games/LEGO Harry Potter 5-7/harry2.exe"
    },
    "files": [
      {
        "dx2010": "https://lutris.net/files/tools/directx-2010.tar.gz"
      },
      {
        "goginstaller": "N/A:Please select the GOG installer"
      }
    ],
    "installer": [
      {
        "task": {
          "arch": "win32",
          "prefix": "$GAMEDIR",
          "name": "create_prefix"
        }
      },
      {
        "extract": {
          "dst": "$CACHE/dxsetup",
          "file": "dx2010"
        }
      },
      {
        "task": {
          "arch": "win32",
          "executable": "$CACHE/dxsetup/DXSETUP.exe",
          "prefix": "$GAMEDIR",
          "name": "wineexec",
          "args": "/silent"
        }
      },
      {
        "task": {
          "arch": "win32",
          "executable": "goginstaller",
          "prefix": "$GAMEDIR",
          "name": "wineexec",
          "args": "/SP- /SUPPRESSMSGBOXES /NOCANCEL /NORESTART"
        }
      }
    ]
  },
  "content": "files:\n- dx2010: https://lutris.net/files/tools/directx-2010.tar.gz\n- goginstaller: N/A:Please select the GOG installer\ngame:\n  arch: win32\n  exe: drive_c/GOG Games/LEGO Harry Potter 5-7/harry2.exe\n  prefix: $GAMEDIR\ninstaller:\n- task:\n    arch: win32\n    name: create_prefix\n    prefix: $GAMEDIR\n- extract:\n    dst: $CACHE/dxsetup\n    file: dx2010\n- task:\n    arch: win32\n    args: /silent\n    executable: $CACHE/dxsetup/DXSETUP.exe\n    name: wineexec\n    prefix: $GAMEDIR\n- task:\n    arch: win32\n    args: /SP- /SUPPRESSMSGBOXES /NOCANCEL /NORESTART\n    executable: goginstaller\n    name: wineexec\n    prefix: $GAMEDIR\n"
}