{
  "name": "Exit Fate",
  "slug": "exit-fate",
  "year": 2009,
  "description": "Daniel is a colonel in the royal army of Kirgard. As Kirgard wages war against its arch rival, the State Union of Zelmony, a series of events leads Daniel astray from the war and his own people. Now he must find out at all costs, the one that has betrayed him.\r\n\r\nGet mesmerized in classic RPG gameplay with as many as 75 playable characters, tons of areas and a huge world to explore. Get engrossed in the deep story-line of Exit Fate in your struggle to come to terms with your past and bring peace to the world, at the same time.",
  "banner_url": "/games/banner/exit-fate.jpg",
  "icon_url": "",
  "is_public": true,
  "updated": "2019-01-23T08:29:26.688960Z",
  "provider_games": [],
  "steamid": null,
  "gogid": null,
  "gogslug": "",
  "humblestoreid": "",
  "id": 15620
}