{
  "name": "Emily is Away",
  "slug": "emily-is-away",
  "year": 2015,
  "description": "Sign In again.\r\nRemember a time before Facebook and Skype? When Windows XP was the next big thing and AIM was king. Relive that era with Emily is Away. Create a screenname and browse buddy infos in this chat-bot meets adventure game. Explore your relationship with Emily, a fellow high school student, in a branching narrative where you choose the outcome. And most importantly, change your text color to lime green so people know you're the coolest kid in school.",
  "banner_url": "/games/banner/emily-is-away.jpg",
  "icon_url": "/games/icon/emily-is-away.png",
  "is_public": true,
  "updated": "2019-04-03T08:46:01.937131Z",
  "provider_games": [],
  "steamid": 417860,
  "gogid": null,
  "gogslug": "",
  "humblestoreid": "",
  "id": 5359
}