{
  "id": 12672,
  "game_id": 26313,
  "game_slug": "the-sims-medieval",
  "name": "The Sims Medieval",
  "year": 2011,
  "user": "citrusalex",
  "runner": "wine",
  "slug": "the-sims-medieval-origin",
  "version": "Origin",
  "description": null,
  "notes": "- Please disable Origin-In-Game to avoid crashing on startup.",
  "created_at": "2019-04-08T05:08:52.902000Z",
  "updated_at": "2019-10-28T20:14:52.329218Z",
  "draft": false,
  "published": true,
  "published_by": 51687,
  "rating": "",
  "steamid": null,
  "gogid": null,
  "gogslug": "",
  "humblestoreid": "",
  "script": {
    "game": {
      "exe": "drive_c/Program Files/Origin/Origin.exe",
      "arch": "win32",
      "prefix": "$GAMEDIR"
    },
    "system": {
      "restore_gamma": true
    },
    "wine": {
      "UseXvidMode": true
    },
    "installer": [
      {
        "task": {
          "arch": "win32",
          "description": "Creating Wine Prefix...",
          "prefix": "$GAMEDIR",
          "name": "create_prefix"
        }
      },
      {
        "task": {
          "prefix": "$GAMEDIR",
          "name": "winekill"
        }
      },
      {
        "task": {
          "app": "dotnet20",
          "arch": "win32",
          "description": "Installing .Net 2.0",
          "prefix": "$GAMEDIR",
          "name": "winetricks",
          "silent": true
        }
      },
      {
        "task": {
          "app": "nocrashdialog",
          "silent": true,
          "description": "Hiding annoying dialogs...",
          "prefix": "$GAMEDIR",
          "name": "winetricks"
        }
      },
      {
        "task": {
          "arch": "win32",
          "description": "Setting version to xp...",
          "prefix": "$GAMEDIR",
          "name": "set_regedit",
          "path": "HKEY_CURRENT_USER\\Software\\Wine",
          "value": "winxp",
          "key": "Version"
        }
      },
      {
        "task": {
          "prefix": "$GAMEDIR",
          "name": "winekill"
        }
      },
      {
        "task": {
          "executable": "origin",
          "exclude_processes": "Origin.exe",
          "description": "Installing Origin...",
          "prefix": "$GAMEDIR",
          "name": "wineexec"
        }
      },
      {
        "task": {
          "prefix": "$GAMEDIR",
          "name": "winekill"
        }
      }
    ],
    "files": [
      {
        "origin": "https://origin-a.akamaihd.net/Origin-Client-Download/origin/legacy/OriginThinSetup.exe"
      }
    ]
  },
  "content": "files:\n- origin: https://origin-a.akamaihd.net/Origin-Client-Download/origin/legacy/OriginThinSetup.exe\ngame:\n  arch: win32\n  exe: drive_c/Program Files/Origin/Origin.exe\n  prefix: $GAMEDIR\ninstaller:\n- task:\n    arch: win32\n    description: Creating Wine Prefix...\n    name: create_prefix\n    prefix: $GAMEDIR\n- task:\n    name: winekill\n    prefix: $GAMEDIR\n- task:\n    app: dotnet20\n    arch: win32\n    description: Installing .Net 2.0\n    name: winetricks\n    prefix: $GAMEDIR\n    silent: true\n- task:\n    app: nocrashdialog\n    description: Hiding annoying dialogs...\n    name: winetricks\n    prefix: $GAMEDIR\n    silent: true\n- task:\n    arch: win32\n    description: Setting version to xp...\n    key: Version\n    name: set_regedit\n    path: HKEY_CURRENT_USER\\Software\\Wine\n    prefix: $GAMEDIR\n    value: winxp\n- task:\n    name: winekill\n    prefix: $GAMEDIR\n- task:\n    description: Installing Origin...\n    exclude_processes: Origin.exe\n    executable: origin\n    name: wineexec\n    prefix: $GAMEDIR\n- task:\n    name: winekill\n    prefix: $GAMEDIR\nsystem:\n  restore_gamma: true\nwine:\n  UseXvidMode: true\n"
}