{
  "name": "High School: Hook Ups",
  "slug": "high-school-hook-ups",
  "year": 2010,
  "platforms": [
    {
      "name": "J2ME"
    }
  ],
  "genres": [
    {
      "name": "Social simulation"
    }
  ],
  "aliases": [],
  "description": "Your objective is to finish high school with the best reputation possible while developing as many friendships as you can. Experience a true-to-life high school experience thanks to typical characters and locations. Find the right words to seduce your love interest, but also to escape the bullies or convince the principal you didn't commit that prank. Forget about grades, High School Hook Ups is all about finding the right one!",
  "banner_url": "/games/banner/high-school-hook-ups.jpg",
  "icon_url": null,
  "is_public": true,
  "updated": "2019-01-23T08:29:50.635213Z",
  "steamid": null,
  "gogslug": "",
  "humblestoreid": ""
}